.DS_Store
MF_intern/__init__.py
MF_intern/main.py
ZOZO_intern/__init__.py
ZOZO_intern/main.py
ZOZO_intern-0.0.1.dist-info/DESCRIPTION.rst
ZOZO_intern-0.0.1.dist-info/LICENSE.txt
ZOZO_intern-0.0.1.dist-info/METADATA
ZOZO_intern-0.0.1.dist-info/RECORD
ZOZO_intern-0.0.1.dist-info/WHEEL
ZOZO_intern-0.0.1.dist-info/metadata.json
ZOZO_intern-0.0.1.dist-info/top_level.txt
