Metadata-Version: 2.0
Name: ZOZO-intern
Version: 0.0.1
Summary: Matrix Factorization
Home-page: https://github.com/MSA8D8/start_today_intern
Author: MSA8D8
Author-email: UNKNOWN
License: MIT
Keywords: Python library for ZOZO intern
Platform: UNKNOWN
Classifier: Development Status :: 3 - Alpha
Classifier: Intended Audience :: Developers
Classifier: Topic :: Software Development :: Build Tools
Classifier: License :: OSI Approved :: MIT License
Classifier: Programming Language :: Python :: 3
Classifier: Programming Language :: Python :: 3.3
Classifier: Programming Language :: Python :: 3.4
Classifier: Programming Language :: Python :: 3.5
Classifier: Programming Language :: Python :: 3.6
